LICENSE
MANIFEST.in
README.rst
setup.py
pyboltz/__init__.py
pyboltz/boltz.py
pyboltz/images/bolt-logo.png
python_boltz.egg-info/PKG-INFO
python_boltz.egg-info/SOURCES.txt
python_boltz.egg-info/dependency_links.txt
python_boltz.egg-info/requires.txt
python_boltz.egg-info/top_level.txt